FactorioSolver/FactorioSolver.py
FactorioSolver/__init__.py
FactorioSolver/data/SpaceAge/default_choice_map.json
FactorioSolver/data/SpaceAge/items.csv
FactorioSolver/data/SpaceAge/recipes.csv
FactorioSolver/data/SpaceExploration/default_choice_map.json
FactorioSolver/data/SpaceExploration/items.csv
FactorioSolver/data/SpaceExploration/recipes.csv
FactorioSolver-0.1.0.dist-info/LICENSE
FactorioSolver-0.1.0.dist-info/METADATA
FactorioSolver-0.1.0.dist-info/WHEEL
FactorioSolver-0.1.0.dist-info/top_level.txt
FactorioSolver-0.1.0.dist-info/RECORD
